LICENCE.txt
MANIFEST.in
README.rst
setup.py
emencia_paste_django/__init__.py
emencia_paste_django/templates.py
emencia_paste_django.egg-info/PKG-INFO
emencia_paste_django.egg-info/SOURCES.txt
emencia_paste_django.egg-info/dependency_links.txt
emencia_paste_django.egg-info/entry_points.txt
emencia_paste_django.egg-info/not-zip-safe
emencia_paste_django.egg-info/requires.txt
emencia_paste_django.egg-info/top_level.txt
emencia_paste_django/django_buildout/+dot+gitignore
emencia_paste_django/django_buildout/Makefile
emencia_paste_django/django_buildout/README.rst
emencia_paste_django/django_buildout/bootstrap.py
emencia_paste_django/django_buildout/buildout.cfg_tmpl
emencia_paste_django/django_buildout/development.cfg
emencia_paste_django/django_buildout/integration.cfg
emencia_paste_django/django_buildout/production.cfg
emencia_paste_django/django_buildout/versions.cfg
emencia_paste_django/django_buildout/compass/+dot+gitignore
emencia_paste_django/django_buildout/compass/README.rst
emencia_paste_django/django_buildout/compass/config.rb
emencia_paste_django/django_buildout/compass/config_f3.rb
emencia_paste_django/django_buildout/compass/scss/_settings.scss
emencia_paste_django/django_buildout/compass/scss/app.scss
emencia_paste_django/django_buildout/compass/scss/flags.scss
emencia_paste_django/django_buildout/compass/scss/components/_addons.scss
emencia_paste_django/django_buildout/compass/scss/components/_contents.scss
emencia_paste_django/django_buildout/compass/scss/components/_icomoon.scss
emencia_paste_django/django_buildout/compass/scss/components/_magnific-popup.scss
emencia_paste_django/django_buildout/compass/scss/components/_pikaday.scss
emencia_paste_django/django_buildout/compass/scss/components/_porticus.scss
emencia_paste_django/django_buildout/compass/scss/components/_royalSlider.scss
emencia_paste_django/django_buildout/compass/scss/components/_socialaggregator.scss
emencia_paste_django/django_buildout/compass/scss/components/_spinner.scss
emencia_paste_django/django_buildout/compass/scss/components/_zinnia.scss
emencia_paste_django/django_buildout/compass/scss_f3/_content.scss
emencia_paste_django/django_buildout/compass/scss_f3/_settings.scss
emencia_paste_django/django_buildout/compass/scss_f3/_tinymce.scss
