Metadata-Version: 1.1
Name: emencia-paste-django
Version: 1.8.2
Summary: Epaster template to build Django projects
Home-page: https://github.com/emencia/emencia-paste-django
Author: David Thenon
Author-email: dthenon@emencia.com
License: MIT
Platform: UNKNOWN
Classifier: Programming Language :: Python
Classifier: License :: OSI Approved :: MIT License
Classifier: Operating System :: OS Independent
Classifier: Development Status :: 5 - Production/Stable
Classifier: Environment :: Web Environment
Classifier: Framework :: Paste
Classifier: Intended Audience :: Developers
Classifier: Topic :: Software Development :: Libraries :: Python Modules
